[
    {
        "auth": "czy1024",
        "cluster_host_override": true,
        "db_scan_limit": 20,
        "host": "127.0.0.1",
        "keys_pattern": "*",
        "lua_keys_loading": false,
        "name": "luna-local",
        "namespace_separator": ":",
        "port": 6379,
        "ssl_ignore_all_errors": false,
        "timeout_connect": 60000,
        "timeout_execute": 60000
    },
    {
        "auth": "czy1024",
        "cluster_host_override": true,
        "db_scan_limit": 20,
        "host": "192.168.31.168",
        "keys_pattern": "*",
        "lua_keys_loading": false,
        "name": "luna-ubuntu",
        "namespace_separator": ":",
        "port": 6379,
        "ssl_ignore_all_errors": false,
        "timeout_connect": 60000,
        "timeout_execute": 60000
    },
    {
        "auth": "czy1024",
        "cluster_host_override": true,
        "db_scan_limit": 20,
        "host": "192.168.31.92",
        "keys_pattern": "*",
        "lua_keys_loading": false,
        "name": "luna-centos",
        "namespace_separator": ":",
        "port": 6379,
        "ssl_ignore_all_errors": false,
        "timeout_connect": 60000,
        "timeout_execute": 60000
    },
    {
        "auth": "czy1024",
        "cluster_host_override": true,
        "db_scan_limit": 20,
        "host": "192.168.1.104",
        "keys_pattern": "*",
        "lua_keys_loading": false,
        "name": "luna-centos",
        "namespace_separator": ":",
        "port": 6379,
        "ssl_ignore_all_errors": false,
        "timeout_connect": 60000,
        "timeout_execute": 60000
    },
    {
        "auth": "czy1024",
        "cluster_host_override": true,
        "db_scan_limit": 20,
        "host": "f.xicc.cc",
        "keys_pattern": "*",
        "lua_keys_loading": false,
        "name": "xicc-exsi-ubuntu",
        "namespace_separator": ":",
        "port": 23515,
        "ssl_ignore_all_errors": false,
        "timeout_connect": 60000,
        "timeout_execute": 60000
    },
    {
        "auth": "czy1024",
        "cluster_host_override": true,
        "db_scan_limit": 20,
        "host": "f.xicc.cc",
        "keys_pattern": "*",
        "lua_keys_loading": false,
        "name": "xicc-exsi-ubuntu",
        "namespace_separator": ":",
        "port": 23415,
        "ssl_ignore_all_errors": false,
        "timeout_connect": 60000,
        "timeout_execute": 60000
    }
]
